dygo/__init__.py
dygo/_version.py
dygo/config.py
dygo/dygo.py
dygo-0.3.1.dist-info/METADATA
dygo-0.3.1.dist-info/WHEEL
dygo-0.3.1.dist-info/licenses/LICENSE
dygo-0.3.1.dist-info/RECORD
