Metadata-Version: 2.4
Name: dygo
Version: 0.3.1
Summary: Dynamic Gooey from config files
Project-URL: Changelog, https://github.com/m-birke/dygo/blob/main/CHANGELOG.md
Project-URL: Documentation, https://github.com/m-birke/dygo#readme
Project-URL: Homepage, https://github.com/m-birke/dygo
Project-URL: Issues, https://github.com/m-birke/dygo/issues
Project-URL: Source, https://github.com/m-birke/dygo
Author-email: m-birke <wesci@web.de>
License-Expression: MIT
License-File: LICENSE
Keywords: gooey,gui,json,jsonpath,yaml
Classifier: Development Status :: 5 - Production/Stable
Classifier: License :: OSI Approved :: MIT License
Classifier: Operating System :: Microsoft :: Windows
Classifier: Operating System :: POSIX :: Linux
Classifier: Programming Language :: Python
Classifier: Programming Language :: Python :: 3.7
Classifier: Programming Language :: Python :: 3.8
Classifier: Programming Language :: Python :: 3.9
Classifier: Programming Language :: Python :: 3.10
Classifier: Programming Language :: Python :: 3.11
Classifier: Programming Language :: Python :: 3.12
Classifier: Programming Language :: Python :: 3.13
Classifier: Programming Language :: Python :: Implementation :: CPython
Classifier: Typing :: Typed
Requires-Python: >=3.7
Requires-Dist: dpath
Requires-Dist: gooey
Requires-Dist: jsonpath-ng
Requires-Dist: pyyaml
